setup.py
dsnd_probability_YH/Binomialdistribution.py
dsnd_probability_YH/Gaussiandistribution.py
dsnd_probability_YH/Generaldistribution.py
dsnd_probability_YH/__init__.py
dsnd_probability_YH.egg-info/PKG-INFO
dsnd_probability_YH.egg-info/SOURCES.txt
dsnd_probability_YH.egg-info/dependency_links.txt
dsnd_probability_YH.egg-info/not-zip-safe
dsnd_probability_YH.egg-info/top_level.txt