Metadata-Version: 1.0
Name: dsnd-probability-YH
Version: 1.6
Summary: Gaussian and Binomial distributions
Home-page: UNKNOWN
Author: Yasin Hassan
Author-email: yasinhassan1243@yahoo.com
License: UNKNOWN
Platform: UNKNOWN
